CHANGES.rst
CONTRIBUTORS.rst
DEVELOP.rst
LICENSE.rst
MANIFEST.in
README.rst
setup.cfg
setup.py
docs/conf.py
docs/index.rst
src/appy/__init__.py
src/appy/version.py
src/appy/pod/__init__.py
src/appy/pod/actions.py
src/appy/pod/buffers.py
src/appy/pod/content.xmlt
src/appy/pod/converter.py
src/appy/pod/doc_importers.py
src/appy/pod/elements.py
src/appy/pod/imageNotFound.jpg
src/appy/pod/metadata.py
src/appy/pod/odf_parser.py
src/appy/pod/parts.py
src/appy/pod/pod_parser.py
src/appy/pod/renderer.py
src/appy/pod/styles.xmlt
src/appy/pod/styles_manager.py
src/appy/pod/xhtml2odt.py
src/appy/pod/xhtml/__init__.py
src/appy/pod/xhtml/parser.py
src/appy/pod/xhtml/tags.py
src/appy/pod/xhtml/visitors.py
src/appy/shared/__init__.py
src/appy/shared/account.py
src/appy/shared/css.py
src/appy/shared/csv_parser.py
src/appy/shared/dates.py
src/appy/shared/dav.py
src/appy/shared/diff.py
src/appy/shared/errors.py
src/appy/shared/google.py
src/appy/shared/ical.py
src/appy/shared/ldap_connector.py
src/appy/shared/odf.py
src/appy/shared/packaging.py
src/appy/shared/sap.py
src/appy/shared/sso.py
src/appy/shared/tables.py
src/appy/shared/test.py
src/appy/shared/utils.py
src/appy/shared/xml_parser.py
src/appy/shared/zip.py
src/appy/shared/data/BelgianCommunes.txt
src/appy/shared/data/CountryCodesIso3166.1.txt
src/appy/shared/data/LanguageCodesIso639.2.txt
src/appy/shared/data/__init__.py
src/collective/__init__.py
src/collective.freeze.egg-info/PKG-INFO
src/collective.freeze.egg-info/SOURCES.txt
src/collective.freeze.egg-info/dependency_links.txt
src/collective.freeze.egg-info/entry_points.txt
src/collective.freeze.egg-info/namespace_packages.txt
src/collective.freeze.egg-info/not-zip-safe
src/collective.freeze.egg-info/requires.txt
src/collective.freeze.egg-info/top_level.txt
src/collective/freeze/__init__.py
src/collective/freeze/configure.zcml
src/collective/freeze/interfaces.py
src/collective/freeze/permissions.zcml
src/collective/freeze/setuphandlers.py
src/collective/freeze/testing.py
src/collective/freeze/upgrades.py
src/collective/freeze/upgrades.zcml
src/collective/freeze/browser/__init__.py
src/collective/freeze/browser/configure.zcml
src/collective/freeze/browser/overrides/.gitkeep
src/collective/freeze/browser/static/.gitkeep
src/collective/freeze/locales/README.rst
src/collective/freeze/locales/__init__.py
