Metadata-Version: 2.1
Name: collective.freeze
Version: 1.6
Summary: An add-on for Plone
Home-page: UNKNOWN
Author: Rob Miller
Author-email: robmr@openplans.org
License: GPL version 2
Keywords: Python Plone
Platform: UNKNOWN
Classifier: Environment :: Web Environment
Classifier: Framework :: Plone
Classifier: Framework :: Plone :: Addon
Classifier: Framework :: Plone :: 4.3
Classifier: Programming Language :: Python
Classifier: Programming Language :: Python :: 2.7
Classifier: Operating System :: OS Independent
Classifier: License :: OSI Approved :: GNU General Public License v2 (GPLv2)
Requires-Python: >=2.7
Provides-Extra: test
